LICENSE
MANIFEST.in
README.rst
setup.py
django_sendgrid_v4.egg-info/PKG-INFO
django_sendgrid_v4.egg-info/SOURCES.txt
django_sendgrid_v4.egg-info/dependency_links.txt
django_sendgrid_v4.egg-info/requires.txt
django_sendgrid_v4.egg-info/top_level.txt
sendgrid_backend/__init__.py
sendgrid_backend/mail.py
sendgrid_backend/version.py
test/test_backend_init.py
test/test_mail.py