Metadata-Version: 1.1
Name: django-sendgrid-v4
Version: 0.6.5a0
Summary: An implementation of Django's EmailBackend compatible with sendgrid-python v4+
Home-page: https://github.com/sklarsa/django-sendgrid-v4
Author: Steven Sklar
Author-email: sklarsa@gmail.com
License: MIT
Keywords: django email sendgrid backend
Platform: UNKNOWN
Classifier: Development Status :: 3 - Alpha
Classifier: Intended Audience :: Developers
Classifier: Programming Language :: Python :: 2
Classifier: Programming Language :: Python :: 2.7
Classifier: Programming Language :: Python :: 3
Classifier: Programming Language :: Python :: 3.4
Classifier: Programming Language :: Python :: 3.5
Classifier: Programming Language :: Python :: 3.6
